setup.cfg
setup.py
forrest/__init__.py
forrest/ssh.py
forrest.egg-info/PKG-INFO
forrest.egg-info/SOURCES.txt
forrest.egg-info/dependency_links.txt
forrest.egg-info/entry_points.txt
forrest.egg-info/requires.txt
forrest.egg-info/top_level.txt
forrest/commands/__init__.py
forrest/commands/run.py
forrest/commands/utils.py
forrest/providers/__init__.py
forrest/providers/azure.py
forrest/providers/ec2.py